ksbox/__init__.py
ksbox-1.0.0.1.dist-info/METADATA
ksbox-1.0.0.1.dist-info/WHEEL
ksbox-1.0.0.1.dist-info/top_level.txt
ksbox-1.0.0.1.dist-info/RECORD
